{
  "generatedAt": "2026-07-19T12:06:31.285Z",
  "note": "Score-band results are empirical outcome rates from graded historical predictions. HR Quality Score is a ranking score, not a calibrated probability — these rates describe what happened, not a validated forecast.",
  "totalGradedRecords": 430,
  "byScoreBand": {
    "80+": {
      "predictions": 0,
      "eligibleGraded": 0,
      "hrHits": 0,
      "actualHrRate": null,
      "avgMarketImpliedProbability": null,
      "avgOdds": null,
      "flatBetRoi": null,
      "calibrationDifference": null,
      "sampleSize": 0
    },
    "70-79.9": {
      "predictions": 5,
      "eligibleGraded": 5,
      "hrHits": 0,
      "actualHrRate": 0,
      "avgMarketImpliedProbability": 28,
      "avgOdds": 271,
      "flatBetRoi": -100,
      "calibrationDifference": null,
      "sampleSize": 5
    },
    "60-69.9": {
      "predictions": 32,
      "eligibleGraded": 32,
      "hrHits": 2,
      "actualHrRate": 6.3,
      "avgMarketImpliedProbability": 23.8,
      "avgOdds": 353,
      "flatBetRoi": -75.2,
      "calibrationDifference": null,
      "sampleSize": 32
    },
    "50-59.9": {
      "predictions": 59,
      "eligibleGraded": 59,
      "hrHits": 12,
      "actualHrRate": 20.3,
      "avgMarketImpliedProbability": 20.6,
      "avgOdds": 415,
      "flatBetRoi": -5.1,
      "calibrationDifference": null,
      "sampleSize": 59
    },
    "Below 50": {
      "predictions": 334,
      "eligibleGraded": 334,
      "hrHits": 34,
      "actualHrRate": 10.2,
      "avgMarketImpliedProbability": 15.3,
      "avgOdds": 628,
      "flatBetRoi": -26.7,
      "calibrationDifference": null,
      "sampleSize": 334
    }
  },
  "byConfidenceLevel": {
    "high": {
      "predictions": 0,
      "eligibleGraded": 0,
      "hrHits": 0,
      "actualHrRate": null,
      "avgMarketImpliedProbability": null,
      "avgOdds": null,
      "flatBetRoi": null,
      "calibrationDifference": null,
      "sampleSize": 0
    },
    "medium": {
      "predictions": 419,
      "eligibleGraded": 419,
      "hrHits": 46,
      "actualHrRate": 11,
      "avgMarketImpliedProbability": 16.9,
      "avgOdds": 571,
      "flatBetRoi": -28.4,
      "calibrationDifference": null,
      "sampleSize": 419
    },
    "low": {
      "predictions": 11,
      "eligibleGraded": 11,
      "hrHits": 2,
      "actualHrRate": 18.2,
      "avgMarketImpliedProbability": null,
      "avgOdds": null,
      "flatBetRoi": null,
      "calibrationDifference": null,
      "sampleSize": 11
    },
    "incomplete": {
      "predictions": 0,
      "eligibleGraded": 0,
      "hrHits": 0,
      "actualHrRate": null,
      "avgMarketImpliedProbability": null,
      "avgOdds": null,
      "flatBetRoi": null,
      "calibrationDifference": null,
      "sampleSize": 0
    }
  },
  "byLineupStatus": {
    "confirmed": {
      "predictions": 90,
      "eligibleGraded": 90,
      "hrHits": 9,
      "actualHrRate": 10,
      "avgMarketImpliedProbability": 15.8,
      "avgOdds": 615,
      "flatBetRoi": -38.5,
      "calibrationDifference": null,
      "sampleSize": 90
    },
    "unconfirmed": {
      "predictions": 340,
      "eligibleGraded": 340,
      "hrHits": 39,
      "actualHrRate": 11.5,
      "avgMarketImpliedProbability": 17.2,
      "avgOdds": 558,
      "flatBetRoi": -25.5,
      "calibrationDifference": null,
      "sampleSize": 340
    }
  },
  "byModelVersion": {
    "mlb-hr-quality-v1.1": {
      "predictions": 430,
      "eligibleGraded": 430,
      "hrHits": 48,
      "actualHrRate": 11.2,
      "avgMarketImpliedProbability": 16.9,
      "avgOdds": 571,
      "flatBetRoi": -28.4,
      "calibrationDifference": null,
      "sampleSize": 430
    }
  },
  "sampleSizeWarning": null,
  "calibrationReadiness": {
    "sampleCount": 430,
    "hrOutcomeCount": 48,
    "calendarDayCount": 4,
    "meetsMinimumThreshold": false,
    "warnings": [
      "Insufficient graded predictions: 430/1000",
      "Insufficient HR outcomes: 48/100",
      "Insufficient calendar-day coverage: 4/28 days"
    ],
    "readyForCalibrationFit": false
  }
}
