{
  "date": "2026-06-17",
  "generatedAt": "2026-06-17T18:04:41.504Z",
  "slatePreview": {
    "slateOverview": "Model ranked 255 hitters for today's slate. The strongest park environments in the top of the board are Great American Ball Park, Daikin Park, American Family Field.",
    "modelNote": "When AI commentary is unavailable, picks fall back to the model's top-ranked hitters using barrel rate, hard-hit rate, exit velocity, park factor, pitcher HR/9, and recent HR form."
  },
  "bestBets": [
    {
      "player": "Juan Soto",
      "team": "NYM",
      "opponent": "CIN",
      "opposingPitcher": "Nick Lodolo",
      "hrScoreRank": 1,
      "topStats": [
        "Pitcher HR VS=65.3",
        "Hard Hit%=49.4"
      ],
      "bullets": [
        "HR score 76.1 (#1)",
        "Pitcher HR VS 65.3 at park 1.25"
      ],
      "hrOddsYes": null,
      "hrValueEdge": null
    },
    {
      "player": "Yordan Alvarez",
      "team": "HOU",
      "opponent": "DET",
      "opposingPitcher": "Casey Mize",
      "hrScoreRank": 2,
      "topStats": [
        "Hard Hit%=53.7",
        "Pitcher HR VS=23.4"
      ],
      "bullets": [
        "HR score 74.2 (#2)",
        "Pitcher HR VS 23.4 at park 1.04"
      ],
      "hrOddsYes": null,
      "hrValueEdge": null
    },
    {
      "player": "Jackson Chourio",
      "team": "MIL",
      "opponent": "CLE",
      "opposingPitcher": "Gavin Williams",
      "hrScoreRank": 3,
      "topStats": [
        "Pitcher HR VS=66.7",
        "Hard Hit%=48.2"
      ],
      "bullets": [
        "HR score 72.0 (#3)",
        "Pitcher HR VS 66.7 at park 1.10"
      ],
      "hrOddsYes": null,
      "hrValueEdge": null
    },
    {
      "player": "James Wood",
      "team": "WSH",
      "opponent": "KC",
      "opposingPitcher": "Luinder Avila",
      "hrScoreRank": 4,
      "topStats": [
        "Hard Hit%=58.2",
        "Pitcher HR VS=42.5"
      ],
      "bullets": [
        "HR score 71.2 (#4)",
        "Pitcher HR VS 42.5 at park 0.98"
      ],
      "hrOddsYes": null,
      "hrValueEdge": null
    },
    {
      "player": "Nick Kurtz",
      "team": "ATH",
      "opponent": "PIT",
      "opposingPitcher": "Braxton Ashcraft",
      "hrScoreRank": 5,
      "topStats": [
        "Hard Hit%=57.5",
        "Pitcher HR VS=28.0"
      ],
      "bullets": [
        "HR score 68.7 (#5)",
        "Pitcher HR VS 28.0 at park 0.96"
      ],
      "hrOddsYes": null,
      "hrValueEdge": null
    }
  ],
  "valueBets": [
    {
      "player": "Mike Trout",
      "team": "LAA",
      "opponent": "AZ",
      "opposingPitcher": "Eduardo Rodriguez",
      "hrScoreRank": 6,
      "topStats": [
        "Hard Hit%=52.0",
        "Pitcher HR VS=44.7"
      ],
      "bullets": [
        "HR score 67.9 (#6)",
        "Pitcher HR VS 44.7 at park 1.01"
      ],
      "hrOddsYes": null,
      "hrValueEdge": null
    },
    {
      "player": "Ben Rice",
      "team": "NYY",
      "opponent": "CWS",
      "opposingPitcher": "Anthony Kay",
      "hrScoreRank": 7,
      "topStats": [
        "Pitcher HR VS=63.0",
        "Hard Hit%=48.0"
      ],
      "bullets": [
        "HR score 66.1 (#7)",
        "Pitcher HR VS 63.0 at park 1.18"
      ],
      "hrOddsYes": null,
      "hrValueEdge": null
    },
    {
      "player": "Drake Baldwin",
      "team": "ATL",
      "opponent": "SF",
      "opposingPitcher": "Adrian Houser",
      "hrScoreRank": 8,
      "topStats": [
        "Hard Hit%=53.8",
        "Pitcher HR VS=44.4"
      ],
      "bullets": [
        "HR score 64.3 (#8)",
        "Pitcher HR VS 44.4 at park 1.03"
      ],
      "hrOddsYes": null,
      "hrValueEdge": null
    }
  ],
  "longshots": [
    {
      "player": "Jake Bauers",
      "team": "MIL",
      "opponent": "CLE",
      "opposingPitcher": "Gavin Williams",
      "hrScoreRank": 9,
      "topStats": [
        "Pitcher HR VS=66.7",
        "Hard Hit%=55.2"
      ],
      "bullets": [
        "HR score 64.3 (#9)",
        "Pitcher HR VS 66.7 at park 1.10"
      ],
      "hrOddsYes": null,
      "hrValueEdge": null
    },
    {
      "player": "Dominic Canzone",
      "team": "SEA",
      "opponent": "BAL",
      "opposingPitcher": "Kyle Bradish",
      "hrScoreRank": 10,
      "topStats": [
        "Pitcher HR VS=49.0",
        "Hard Hit%=48.9"
      ],
      "bullets": [
        "HR score 63.9 (#10)",
        "Pitcher HR VS 49.0 at park 0.93"
      ],
      "hrOddsYes": null,
      "hrValueEdge": null
    }
  ]
}
