{
  "date": "2026-06-11",
  "generatedAt": "2026-06-11T11:20:32.581Z",
  "slatePreview": {
    "slateOverview": "Coors Field and Camden Yards stand out as the primary power environments today, while Citi Field offers a slight boost against right-handers. Hunter Dobbins and Zebby Matthews represent the most vulnerable arms on the slate, setting up favorable conditions for Juan Soto and Dillon Dingler. Coors' extreme park factor also elevates both Hunter Goodman and Pete Crow-Armstrong despite tougher pitching matchups.",
    "modelNote": "The model heavily weights barrel rate, hard-hit metrics, and park factors, which is why Soto and Dingler lead the slate despite modest recent HR totals."
  },
  "bestBets": [
    {
      "player": "Juan Soto",
      "team": "NYM",
      "opponent": "STL",
      "opposingPitcher": "Hunter Dobbins",
      "hrScoreRank": 1,
      "topStats": [
        "barrelRate=16.2",
        "hrScore=70.7"
      ],
      "bullets": [
        "Park factor 1.06 at Citi Field",
        "Opposing pitcher HR/9 of 75.7"
      ],
      "hrOddsYes": null,
      "hrValueEdge": null
    },
    {
      "player": "Dillon Dingler",
      "team": "DET",
      "opponent": "MIN",
      "opposingPitcher": "Zebby Matthews",
      "hrScoreRank": 2,
      "topStats": [
        "hardHitRate=52",
        "hrScore=70.3"
      ],
      "bullets": [
        "Last 7 days 2 HR",
        "Exit velo 90.9"
      ],
      "hrOddsYes": null,
      "hrValueEdge": null
    },
    {
      "player": "Hunter Goodman",
      "team": "COL",
      "opponent": "CHC",
      "opposingPitcher": "Edward Cabrera",
      "hrScoreRank": 3,
      "topStats": [
        "parkFactor=1.4",
        "hrScore=67.1"
      ],
      "bullets": [
        "Last 7 days 3 HR",
        "Pull rate 52.7"
      ],
      "hrOddsYes": null,
      "hrValueEdge": null
    },
    {
      "player": "Shohei Ohtani",
      "team": "LAD",
      "opponent": "PIT",
      "opposingPitcher": "Mitch Keller",
      "hrScoreRank": 4,
      "topStats": [
        "hardHitRate=52.5",
        "hrScore=65.7"
      ],
      "bullets": [
        "Exit velo 93.4",
        "Barrel rate 15.9"
      ],
      "hrOddsYes": null,
      "hrValueEdge": null
    },
    {
      "player": "Jac Caglianone",
      "team": "KC",
      "opponent": "TEX",
      "opposingPitcher": "Kumar Rocker",
      "hrScoreRank": 5,
      "topStats": [
        "hardHitRate=58.7",
        "hrScore=65.6"
      ],
      "bullets": [
        "Exit velo 93.9",
        "Last 7 days 2 HR"
      ],
      "hrOddsYes": null,
      "hrValueEdge": null
    }
  ],
  "valueBets": [
    {
      "player": "Pete Crow-Armstrong",
      "team": "CHC",
      "opponent": "COL",
      "opposingPitcher": "Ryan Feltner",
      "hrScoreRank": 6,
      "topStats": [
        "parkFactor=1.4",
        "hrScore=65.5"
      ],
      "bullets": [
        "Opposing pitcher HR/9 of 70.9",
        "Last 30 days 7 HR"
      ],
      "hrOddsYes": null,
      "hrValueEdge": null
    },
    {
      "player": "Nelson Velázquez",
      "team": "STL",
      "opponent": "NYM",
      "opposingPitcher": "Christian Scott",
      "hrScoreRank": 7,
      "topStats": [
        "hardHitRate=64.7",
        "hrScore=65"
      ],
      "bullets": [
        "Barrel rate 17.6",
        "ISO 0.318"
      ],
      "hrOddsYes": null,
      "hrValueEdge": null
    },
    {
      "player": "Pete Alonso",
      "team": "BAL",
      "opponent": "SEA",
      "opposingPitcher": "Bryan Woo",
      "hrScoreRank": 9,
      "topStats": [
        "exitVelo=95",
        "hrScore=62"
      ],
      "bullets": [
        "Last 7 days 2 HR",
        "Park factor 1.1"
      ],
      "hrOddsYes": null,
      "hrValueEdge": null
    },
    {
      "player": "Jared Young",
      "team": "NYM",
      "opponent": "STL",
      "opposingPitcher": "Hunter Dobbins",
      "hrScoreRank": 8,
      "topStats": [
        "Pitcher HR VS=75.7",
        "Hard Hit%=51.1"
      ],
      "bullets": [
        "HR score 62.8 (#8)",
        "Pitcher HR VS 75.7 at park 1.06"
      ],
      "hrOddsYes": null,
      "hrValueEdge": null
    }
  ],
  "longshots": [
    {
      "player": "Tyler Callihan",
      "team": "PIT",
      "opponent": "LAD",
      "opposingPitcher": "Justin Wrobleski",
      "hrScoreRank": 10,
      "topStats": [
        "hrFBRatio=16.7",
        "hrScore=61.8"
      ],
      "bullets": [
        "Barrel rate 30",
        "Pull rate 70"
      ],
      "hrOddsYes": null,
      "hrValueEdge": null
    },
    {
      "player": "Byron Buxton",
      "team": "MIN",
      "opponent": "DET",
      "opposingPitcher": "Keider Montero",
      "hrScoreRank": 11,
      "topStats": [
        "barrelRate=18.5",
        "hrScore=61.5"
      ],
      "bullets": [
        "Last 30 days 7 HR",
        "ISO 0.306"
      ],
      "hrOddsYes": null,
      "hrValueEdge": null
    },
    {
      "player": "Pete Alonso",
      "team": "BAL",
      "opponent": "SEA",
      "opposingPitcher": "Bryan Woo",
      "hrScoreRank": 9,
      "topStats": [
        "Hard Hit%=55.8",
        "Pitcher HR VS=33.3"
      ],
      "bullets": [
        "HR score 62.0 (#9)",
        "Pitcher HR VS 33.3 at park 1.10"
      ],
      "hrOddsYes": null,
      "hrValueEdge": null
    }
  ]
}
