{
  "schemaVersion": "nflverse-personnel-cache-v0.1",
  "provider": "nflverse",
  "season": 2026,
  "retrievedAt": "2026-07-17T12:00:00.000Z",
  "datasets": [
    {
      "dataset": "playerStats",
      "family": "player_stats_season",
      "release": "player_stats",
      "filename": "player_stats_season_2025.csv",
      "sourceUrl": "https://github.com/nflverse/nflverse-data/releases/download/player_stats/player_stats_season.csv",
      "cachePath": "scripts/fixtures/nfl-personnel/nflverse/player_stats_season_2025.csv",
      "sourceUpdatedAt": null,
      "byteSize": 898,
      "sha256": "5c959d5a67be1766ec7dbfc638efbd5fef0038daa6caaa5d51ad1b935c4e6db9",
      "rowCount": 12,
      "headerColumns": [
        "attempts",
        "carries",
        "player_display_name",
        "player_id",
        "position",
        "receiving_yards",
        "recent_team",
        "receptions",
        "rushing_yards",
        "sacks",
        "season",
        "season_type",
        "targets"
      ],
      "pfrDerived": false
    },
    {
      "dataset": "rosters",
      "family": "rosters",
      "release": "rosters",
      "filename": "roster_2026.csv",
      "sourceUrl": "https://github.com/nflverse/nflverse-data/releases/download/rosters/roster_2026.csv",
      "cachePath": "scripts/fixtures/nfl-personnel/nflverse/roster_2026.csv",
      "sourceUpdatedAt": null,
      "byteSize": 1027,
      "sha256": "fa6dc42f09000c007670834213f38baa34ed2c050b4f52e43b29b77d3eed7801",
      "rowCount": 12,
      "headerColumns": [
        "depth_chart_position",
        "espn_id",
        "fantasy_data_id",
        "full_name",
        "gsis_id",
        "pff_id",
        "pfr_id",
        "position",
        "rotowire_id",
        "season",
        "sleeper_id",
        "sportradar_id",
        "status",
        "team",
        "yahoo_id",
        "years_exp"
      ],
      "pfrDerived": false
    },
    {
      "dataset": "snapCounts",
      "family": "snap_counts",
      "release": "snap_counts",
      "filename": "snap_counts_2025.csv",
      "sourceUrl": "https://github.com/nflverse/nflverse-data/releases/download/snap_counts/snap_counts_2025.csv",
      "cachePath": "scripts/fixtures/nfl-personnel/nflverse/snap_counts_2025.csv",
      "sourceUpdatedAt": null,
      "byteSize": 1190,
      "sha256": "51c429b2e0ec9f9f4ca94cb7f5e6cd26ffa10f780690a273f2683d86b92a9c9d",
      "rowCount": 12,
      "headerColumns": [
        "defense_pct",
        "defense_snaps",
        "game_id",
        "game_type",
        "offense_pct",
        "offense_snaps",
        "opponent",
        "pfr_game_id",
        "pfr_player_id",
        "player",
        "position",
        "season",
        "st_pct",
        "st_snaps",
        "team",
        "week"
      ],
      "pfrDerived": true
    }
  ]
}
